[
  {
    "tid": 20801,
    "title": "凤凰彩票特邀88一水。无限制",
    "author": "大象"
  },
  {
    "tid": 20804,
    "title": "【盛世国际SSGG】—✅—(送5)",
    "author": "rfhuj555"
  },
  {
    "tid": 20807,
    "title": "【开元596】神秘彩金",
    "author": "ZJW2007"
  },
  {
    "tid": 20808,
    "title": "盛世回归彩金 充值过的可以去看看",
    "author": "zxy578424"
  },
  {
    "tid": 20809,
    "title": "【飞机注册u台合集】",
    "author": "猫"
  },
  {
    "tid": 20810,
    "title": "飞机台白嫖大合集",
    "author": "chc204"
  },
  {
    "tid": 20814,
    "title": "支付宝十元无门槛",
    "author": "zxy999zxy"
  },
  {
    "tid": 20815,
    "title": "新葡京773无限罚流水账号充了几千块",
    "author": "m992022"
  }
]