[
  {
    "tid": 18385,
    "title": "904彩金",
    "author": "团饭弟"
  },
  {
    "tid": 18386,
    "title": "威尼斯4444回馈彩金",
    "author": "清雪"
  },
  {
    "tid": 18389,
    "title": "新葡京079专属客服彩金",
    "author": "清雪"
  },
  {
    "tid": 18392,
    "title": "瑰丽直播电话特邀",
    "author": "清雪"
  },
  {
    "tid": 18397,
    "title": "新葡京5699神秘彩金",
    "author": "清雪"
  },
  {
    "tid": 18405,
    "title": "[全球彩]腾讯微视截图送8-38",
    "author": "liu130"
  },
  {
    "tid": 18406,
    "title": "博天堂连续领18",
    "author": "黑🐎"
  },
  {
    "tid": 18408,
    "title": "【澳门新葡京】—✅—电话彩金",
    "author": "该来了"
  }
]